vogon/__init__.py
vogon/config.py
vogon/vogon.py
vogon-0.1.4.dist-info/METADATA
vogon-0.1.4.dist-info/WHEEL
vogon-0.1.4.dist-info/top_level.txt
vogon-0.1.4.dist-info/RECORD
