Metadata-Version: 2.1
Name: vogon
Version: 0.1.4
Summary: A basic data aggregator for astrophysical transients
Author: Thomas Moore
Author-email: tmoore11@qub.ac.uk
Requires-Python: >=3.7
Requires-Dist: pandas
Requires-Dist: astropy
Requires-Dist: requests
Requires-Dist: lasair
Requires-Dist: tqdm
Requires-Dist: matplotlib
Requires-Dist: plotly
Requires-Dist: nbformat >=4.2.0
Requires-Dist: kaleido
